[{"Transaction Date":"03/03", "Merchant":"Internet Payment", "Category":"Payments And Credits", "Amount":"$328.73"}, {"Transaction Date":"02/04", "Merchant":"Hollister #31393", "Category":"Merchandise", "Amount":"$13.20"}, {"Transaction Date":"02/04", "Merchant":"Columbia 419", "Category":"Merchandise", "Amount":"$18.69"}, {"Transaction Date":"02/04", "Merchant":"Tommy Hilfiger", "Category":"Merchandise", "Amount":"$37.96"}, {"Transaction Date":"02/07", "Merchant":"MA SABI Metro STL", "Category":"Travel/Entertainment", "Amount":"$1.00"}, {"Transaction Date":"02/14", "Merchant":"408 Foundry", "Category":"Supermarkets", "Amount":"$59.26"}, {"Transaction Date":"02/28", "Merchant":"HULU", "Category":"Merchandise", "Amount":"$20.00"}, {"Transaction Date":"02/29", "Merchant":"408 Foundry", "Category":"Supermarkets", "Amount":"$43.52"}, {"Transaction Date":"03/02", "Merchant":"Schnucks Lindell", "Category":"Supermarkets", "Amount":"$64.76"}, {"Transaction Date":"02/26", "Merchant":"HULU", "Category":"Services", "Amount":"$1.99"}, {"Transaction Date":"03/02", "Merchant":"Chat Subscription", "Category":"Merchandise", "Amount":"$20.00"}]